<?xml version="1.0" encoding="utf-8" standalone="no"?>
<installer-gui-script minSpecVersion="1">
    <title>tree {{version}}</title>

    <background alignment="center" file="background.png" mime-type="image/png" scaling="tofit"/>
    <welcome file="welcome.html" mime-type="text/html"/>
    <license file="license.html" mime-type="text/html"/>

    <options customize="never"/>

    <choices-outline>
        <line choice="com.ablepear.tree"/>
    </choices-outline>

    <choice id="com.ablepear.tree">
        <pkg-ref id="com.ablepear.tree"/>
    </choice>
    <pkg-ref id="com.ablepear.httperf">tree-{{version}}.pkg</pkg-ref>

</installer-gui-script>
